brcurrency/bitcoin.py
brcurrency/bitcoincash.py
brcurrency/dolar.py
brcurrency/ethereum.py
brcurrency/ethereumclassic.py
brcurrency/euro.py
brcurrency/iene.py
brcurrency/libra.py
brcurrency/litecoin.py
brcurrency/monero.py
brcurrency/nano.py
brcurrency/neo.py
BRCurrencyPy-0.3.dist-info/METADATA
BRCurrencyPy-0.3.dist-info/WHEEL
BRCurrencyPy-0.3.dist-info/top_level.txt
BRCurrencyPy-0.3.dist-info/RECORD
